kymotools/__init__.py
kymotools/detect.py
kymotools/interactive.py
kymotools/io.py
kymotools/kymo.py
kymotools/msd.py
kymotools/resources/fonts/Roboto-Regular.ttf
kymotools/utils/__init__.py
kymotools/utils/fileutils.py
kymotools/utils/imageutils.py
kymotools-0.4.10.dist-info/licenses/LICENSE
kymotools-0.4.10.dist-info/METADATA
kymotools-0.4.10.dist-info/WHEEL
kymotools-0.4.10.dist-info/top_level.txt
kymotools-0.4.10.dist-info/RECORD
