Metadata-Version: 2.4
Name: kymotools
Version: 0.4.10
Summary: Scripts for kymograph processing
Author-email: Stephen Cross <stephen.cross@bristol.ac.uk>
License:                     GNU GENERAL PUBLIC LICENSE
Project-URL: Homepage, https://github.com/sjcross/kymotools
Project-URL: Issues, https://github.com/sjcross/kymotools/issues
Project-URL: Repository, https://github.com/sjcross/kymotools.git
Keywords: kymo,kymograph
Classifier: Programming Language :: Python :: 3
Classifier: License :: OSI Approved :: GNU General Public License v3 (GPLv3)
Classifier: Operating System :: OS Independent
Requires-Python: >=3.8
License-File: LICENSE
Requires-Dist: matplotlib>=3.0.0
Requires-Dist: scipy>=1.0.0
Requires-Dist: tifffile>=2021.1.8
Requires-Dist: tqdm>=4.1.0
Dynamic: license-file
